matrix_synapse_ray-1.12.0.4.data/scripts/export_signing_key
matrix_synapse_ray-1.12.0.4.data/scripts/generate_config
matrix_synapse_ray-1.12.0.4.data/scripts/generate_log_config
matrix_synapse_ray-1.12.0.4.data/scripts/generate_signing_key.py
matrix_synapse_ray-1.12.0.4.data/scripts/hash_password
matrix_synapse_ray-1.12.0.4.data/scripts/move_remote_media_to_new_store.py
matrix_synapse_ray-1.12.0.4.data/scripts/register_new_matrix_user
matrix_synapse_ray-1.12.0.4.data/scripts/synapse_port_db
matrix_synapse_ray-1.12.0.4.data/scripts/sync_room_to_group.pl
matrix_synapse_ray-1.12.0.4.data/scripts/synctl
synapse/__init__.py
synapse/event_auth.py
synapse/notifier.py
synapse/python_dependencies.py
synapse/secrets.py
synapse/server.py
synapse/server.pyi
synapse/types.py
synapse/visibility.py
synapse/_scripts/__init__.py
synapse/_scripts/register_new_matrix_user.py
synapse/api/__init__.py
synapse/api/auth.py
synapse/api/constants.py
synapse/api/errors.py
synapse/api/filtering.py
synapse/api/ratelimiting.py
synapse/api/room_versions.py
synapse/api/urls.py
synapse/app/__init__.py
synapse/app/_base.py
synapse/app/admin_cmd.py
synapse/app/appservice.py
synapse/app/client_reader.py
synapse/app/event_creator.py
synapse/app/federation_reader.py
synapse/app/federation_sender.py
synapse/app/frontend_proxy.py
synapse/app/generic_worker.py
synapse/app/homeserver.py
synapse/app/media_repository.py
synapse/app/pusher.py
synapse/app/synchrotron.py
synapse/app/user_dir.py
synapse/appservice/__init__.py
synapse/appservice/api.py
synapse/appservice/scheduler.py
synapse/config/__init__.py
synapse/config/__main__.py
synapse/config/_base.py
synapse/config/_base.pyi
synapse/config/api.py
synapse/config/appservice.py
synapse/config/captcha.py
synapse/config/cas.py
synapse/config/consent_config.py
synapse/config/database.py
synapse/config/emailconfig.py
synapse/config/groups.py
synapse/config/homeserver.py
synapse/config/jitsi.py
synapse/config/jwt_config.py
synapse/config/key.py
matrix_synapse_ray-1.12.0.4.dist-info/AUTHORS.rst
matrix_synapse_ray-1.12.0.4.dist-info/LICENSE
matrix_synapse_ray-1.12.0.4.dist-info/METADATA
matrix_synapse_ray-1.12.0.4.dist-info/WHEEL
matrix_synapse_ray-1.12.0.4.dist-info/top_level.txt
matrix_synapse_ray-1.12.0.4.dist-info/RECORD
