Metadata-Version: 2.1
Name: matrix-synapse-ray
Version: 1.12.0.4
Summary: Reference homeserver for the Matrix decentralised comms protocol
Home-page: UNKNOWN
License: UNKNOWN
Platform: UNKNOWN
Classifier: Development Status :: 5 - Production/Stable
Classifier: Topic :: Communications :: Chat
Classifier: License :: OSI Approved :: Apache Software License
Classifier: Programming Language :: Python :: 3 :: Only
Classifier: Programming Language :: Python :: 3.5
Classifier: Programming Language :: Python :: 3.6
Classifier: Programming Language :: Python :: 3.7
Requires-Python: ~=3.5
Requires-Dist: jsonschema (>=2.5.1)
Requires-Dist: frozendict (>=1)
Requires-Dist: unpaddedbase64 (>=1.1.0)
Requires-Dist: canonicaljson (>=1.1.3)
Requires-Dist: signedjson (>=1.1.0)
Requires-Dist: pynacl (>=1.2.1)
Requires-Dist: idna (>=2.5)
Requires-Dist: service-identity (>=18.1.0)
Requires-Dist: Twisted (>=18.9.0)
Requires-Dist: treq (>=15.1)
Requires-Dist: pyopenssl (>=16.0.0)
Requires-Dist: pyyaml (>=3.11)
Requires-Dist: pyasn1 (>=0.1.9)
Requires-Dist: pyasn1-modules (>=0.0.7)
Requires-Dist: daemonize (>=2.3.1)
Requires-Dist: bcrypt (>=3.1.0)
Requires-Dist: pillow (>=4.3.0)
Requires-Dist: sortedcontainers (>=1.4.4)
Requires-Dist: pymacaroons (>=0.13.0)
Requires-Dist: msgpack (>=0.5.2)
Requires-Dist: phonenumbers (>=8.2.0)
Requires-Dist: six (>=1.10)
Requires-Dist: prometheus-client (<0.8.0,>=0.0.18)
Requires-Dist: attrs (>=17.4.0)
Requires-Dist: netaddr (>=0.7.18)
Requires-Dist: Jinja2 (>=2.9)
Requires-Dist: bleach (>=1.4.3)
Requires-Dist: typing-extensions (>=3.7.4)
Provides-Extra: acme
Requires-Dist: txacme (>=0.9.2) ; extra == 'acme'
Requires-Dist: eliot (<1.8.0) ; (python_version < "3.5.3") and extra == 'acme'
Provides-Extra: all
Requires-Dist: pysaml2 (>=4.5.0) ; extra == 'all'
Requires-Dist: lxml (>=3.5.0) ; extra == 'all'
Requires-Dist: opentracing (>=2.2.0) ; extra == 'all'
Requires-Dist: parameterized ; extra == 'all'
Requires-Dist: jaeger-client (>=4.0.0) ; extra == 'all'
Requires-Dist: mock (>=2.0) ; extra == 'all'
Requires-Dist: psycopg2 (>=2.7) ; extra == 'all'
Requires-Dist: txacme (>=0.9.2) ; extra == 'all'
Requires-Dist: pyjwt (>=1.6.4) ; extra == 'all'
Requires-Dist: Jinja2 (>=2.9) ; extra == 'all'
Requires-Dist: sentry-sdk (>=0.7.2) ; extra == 'all'
Requires-Dist: matrix-synapse-ldap3 (>=0.1) ; extra == 'all'
Requires-Dist: eliot (<1.8.0) ; (python_version < "3.5.3") and extra == 'all'
Provides-Extra: jwt
Requires-Dist: pyjwt (>=1.6.4) ; extra == 'jwt'
Provides-Extra: matrix-synapse-ldap3
Requires-Dist: matrix-synapse-ldap3 (>=0.1) ; extra == 'matrix-synapse-ldap3'
Provides-Extra: opentracing
Requires-Dist: jaeger-client (>=4.0.0) ; extra == 'opentracing'
Requires-Dist: opentracing (>=2.2.0) ; extra == 'opentracing'
Provides-Extra: postgres
Requires-Dist: psycopg2 (>=2.7) ; extra == 'postgres'
Provides-Extra: resources.consent
Requires-Dist: Jinja2 (>=2.9) ; extra == 'resources.consent'
Provides-Extra: saml2
Requires-Dist: pysaml2 (>=4.5.0) ; extra == 'saml2'
Provides-Extra: sentry
Requires-Dist: sentry-sdk (>=0.7.2) ; extra == 'sentry'
Provides-Extra: systemd
Requires-Dist: systemd-python (>=231) ; extra == 'systemd'
Provides-Extra: test
Requires-Dist: mock (>=2.0) ; extra == 'test'
Requires-Dist: parameterized ; extra == 'test'
Provides-Extra: url_preview
Requires-Dist: lxml (>=3.5.0) ; extra == 'url_preview'
